Workbook

Sheet G50-01
L2: Serie G. N°50 (2025)
A3: DIRECTION GENERALE DES IMPOTS | D3: Année: | E3: 2026 | H3: IMPOTS ET TAXES PERCUS AU COMPTANT
B4: Direction des Impôts | H4: OU PAR VOIE DE RETENUE A LA SOURCE
A5: Wilaya de : | B5: SIDI BEL ABBES | D5: Mois : | E5: MAI | H5: DECLARATION TENANT LIEU DE BORDEREAU-AVIS DE VERSEMENT
B6: Inspection des impôts | D6: Trimestre
A7: de : | B7: DGE | C7: SIDI BEL ABBES | H7: M. | I7: SEKRANE BOUZIANE
B8: Recette des impôts | D8: A rappeler
A9: de : | B9: DGE | C9: SIDI BEL ABBES | D9: obligatoirement | H9: Activité: | I9: SERVICES TRANSPORT & GROUPE COMMERCIAL DOUAA-BUSNESS
A10: Commune: | H10: Adresse: | I10: CITE DERRAR ESSALAMA N°48
C11: 1.9763102e+15 | D11: Identifiant fiscal / N.I.S | J11: SIDI BEL ABBES | L11: CODE ACTIVITE
C12: 2245000012 | D12: Article d'imposition
C13: 10000036242 | D13: BP
A15: IBS/ ICBS : Acompte / Solde de liquidation
A16: Code | B16: Acompte /solde de liquidation IBS/ICBS | I16: Détermination de l’acompte provisionnel/ solde de liquidation | L16: Montant à payer (DA)
A17: E1M10 | B17: Acompte provisionnel IBS N°2 2025 | L17: 0
B18: Solde de liquidation IBS
B19: Acompte provisionnel ICBS | L19: =I19*30% -> 0
B20: Solde de liquidation ICBS
A21: 1 | B21: TOTAL | L21: =SUM(L17:L20) -> 0
C24: IBS : Retenues à la source
A25: Code | C25: Catégories de revenus soumis à une retenue à la source IBS | I25: Base imposable | K25: Taux | L25: Montant à payer (DA)
A26: E1M30 | C26: IBS/Revenus des entreprises étrangères non installées en Algérie (prestations de services) (1) | K26: ……………….…%
A27: E1M40 | C27: IBS/Autres retenues à la source | K27: ……………….…%
A28: 2 | B28: (1)Joindre le relevé détaillé des retenues à la source par entreprise. | I28: TOTAL
C30: IRG (BIC/BNC/RA): Acompte / Solde de liquidation
A31: Code | C31: Acompte/ Solde de liquidation | H31: Détermination de l’acompte provisionnel/ solde de liquidation | L31: Montant à payer (DA)
B32: Acompte provisionnel N°02 2025 | I32: 2emm acompt 2026 | J32: 702522 | K32: 0.3 | L32: =+J32*K32 -> 210756.6
B33: Solde de liquidation
A34: 3 | B34: TOTAL | L34: =+L32 -> 210756.6
A36: IRG / Traitements et salaires et autres retenues à la source
A37: CODE | D37: Catégories de revenus soumis à une retenue à la source | J37: Revenu imposable | K37: Taux | L37: MONTANT A payer (D.A)
A38: IRG/Salaires | C38: E1L20 | D38: IRG / Traitements,salaires, pensions et rentes viagères | K38: Barème
A39: Autres | C39: E1L30 | D39: IRG / RCDC (titres nominatifs) | K39: 0.1
A40: retenues | C40: E1L40 | D40: IRG / Bénéfices distribués par les sociétés de capitaux | K40: 0.1
A41: IRG | C41: E1L60 | D41: IRG / Revenus des bons de caisse anonymes | K41: 0.3
C42: E1L80 | D42: IRG / Autres retenues à la source | K42: 0.15 | L42: =IF(K42<>"",ROUNDDOWN(J42*K42,0),0) -> 0
A43: Retenues | C43: E1M30 | D43: IBS / Entreprises étrangères non installées (Prest. services) (1) | K43: 0.24
A44: IBS | C44: E1M40 | D44: IBS / Autres retenues à la source
A45: 4 | D45: (1) Joindre relevé détaillé des retenues | I45: TOTAL | J45: =SUM(J38:J44) -> 0 | L45: =SUM(L38:L44) -> 0

Sheet G50-02
A3: TAXE LOCALE DE SOLIDARITE ( T.L.S )
A4: Code | B4: Opérations Imposables | C4: Chiffre d'affaires | D4: Chiffre d'affaires Imposables Recette Professionnelles imposables | E4: TAUX | F4: Montant à payer (DA)
C5: Total
B6: 1-Régime paiement mensuel :
B7: 1) Activité de transport par canalisation des hydrocarbures : | E7: 0.03
B8: 2) Activité miniéres : | E8: 0.015
B9: Opérations sans réfaction : ………………… | F9: =+D9*0.015 -> 0
B10: Opération bénéficent de la réfaction de 30% ……………. | F10: =+D10*0.015 -> 0
B11: Opérations exonéréés ou non imposables
B12: -AAPI …………………………32%…………………… | F12: =+D12*0.015 -> 0
B13: -ANDI ………………………………………………
B14: -ANSEJ……………………………………………… | F14: =+C14 -> 0
B15: -ANGEM ……………………………………………… | F15: =+C15 -> 0
B16: -CNAC ………………………………………………
B17: -Opérations Intra groupe ………………………………………………
B18: -Opérations Inter-Unités ……………………………………
B19: -Autres………………………………………………
A21:  Option pour le régime des acomptes provisionnels (1
B22: II-Régime des acomptes provisionneles
B23: 1) Activité de transport par canalisation des hydrocarbures : | E23: 0.03
B24: Période de référence………………………….. Ou Date et montant notifié………………………………..
B25:  Montant de l’acompte …………………………………..
B26:  Montant du solde de liquidation………………………
B27: 2) Activité miniéres : | E27: 0.015
B28: Période de référence………………………….. Ou Date et montant notifié………………………………..
B29:  Montant de l’acompte …………………………………..
B30:  Montant du solde de liquidation………………………
A32: 4 | B32: TOTAL GENERAL DES C.A | C32: =SUM(C6:C31) -> 0 | D32: =SUM(D8:D25) -> 0 | F32: =SUM(F6:F31) -> 0

Sheet G50-03
J1: =+'[2]G.50-1'!A12 -> 0
I3: ='[2]G.50-1'!E3 -> 2025
D4: Opérations imposables | H4: CA imposable | I4: Taux | J4: A payer (D.A)
A5: Droit de | C5: E2E00 | D5: ='[1]Saisie-chiffres'!D74 -> Timbre de quittances | E5: MAI | I5: 0.01
A6: Timbre | I6: 0.015
A7: Sur Etat | I7: 0.02
A8: 5 | F8: TOTAL | H8: =+H5 -> 0 | J8: =SUM(J5:J7) -> 0 | K8: =A8 -> 5
D10: Opérations imposables | H10: CA imposable | I10: Taux | J10: A payer (D.A)
A11: Impôts et taxes
A12: non repris | I12: 0.01 | J12: =+H12*1% -> 0
A13: ci-dessus | I13: 0.01 | J13: =+H13*1% -> 0
A14: 6 | F14: TOTAL | H14: =SUM(H11:H13) -> 0 | J14: =SUM(J11:J13) -> 0 | K14: =A14 -> 6
C16: RECAPITULATION (EN D.A) | F16: Cadre réservé au contribuable | H16: Cadre réservé à la recette | J16: Cadre resérvé à l'inspection
H17: Reçu ce jour la présente | J17: Eenregistrée le :
A18: 1 - TAP | B18: AP/SL-IBS/ICBS | D18: C/500026/A | E18: =+'G50-01'!L21 -> 0 | F18: Certifie sincère et véritable | H18: déclaration enregistrée | J18: ………………………………………
A19: 2 - AP/IBS | B19: IRG/Retenues à la source | D19: C/201001/M1 | E19: 0 | F19: le contenu de la présente | H19: sous le n° ………………….. | J19: Observarions éventuelles
A20: 3 - AP/SL-IRG (BIC/BNC) et AP/RA | D20: C/500026/C | E20: =+'G50-01'!L34 -> 210756.6 | F20: déclaration conforme | H20: Payée par | J20: ………………………………………
A21: 3/1 - IRG/Salaires | D21: C/201001/100 | F21: aux documents comptables | H21: Chq banque N°………………… | J21: ………………………………………
A22: 3/2 - IRG/Autres retenues | D22: C/201001/101/A/B/C | F22: A : | G22: SIDI BEL ABBES | H22: du …….......Agence……… | J22: ………………………………………
A23: 3/3 - IBS Ret. à la source | D23: C/201001/M2 et 3 | F23: le : | G23: 46178 | H23: Chq poste……… du…………. | J23: ………………………………………
A24: =" - "&D11 -> - | D24: C/201003/303/A/B | E24: =J11 -> 0 | J24: ………………………………………
A25: 4- T. L. S | D25: C/ | F25: Cachet, Signature | H25: Prise en recette | J25: =SUM(J12:J24) -> 0
A26: 5 - Droit de timbre | D26: C/201002/201 | E26: =SUM(J8) -> 0 | H26: par quit. N° ………………… | J26: ………………………………………
A27: =" 6 - "&D166 -> 6 - | B27: AutresTFPP-2025-GC+TRANSPORT | D27: C/…………… | E27: =+J14 -> 0 | H27: A ………..…le……………… | J27: ………………………………………
A28: 7 - TVA | D28: C/201003/300/A/B/C | E28: =+'G50-04'!L38 -> 0 | H28: Le receveur des impôts | J28: ………………………………………
H29: Cachet, Signature | J29: ………………………………………
B30: MONTANT TOTAL A PAYER | E30: =SUM(E18:E29) -> 210756.6

Sheet G50-04
B2: Les chiffres d'affaires et les revenus sont inscrits | D2: TAXE SUR LA VALEUR AJOUTEE
B3: en dinars, le dernier chiffre étant ramené au zéro | E3: 2026
B4: Exemple 325.626 DA = 325.620 | D4: A/ Chiffres d'affaires imposables | L4: 46113
E5: MAI
B6: Code | D6: Chiffre d'affaires | F6: Chiffre d'affaires | I6: Chiffre d'affaires | J6: Taux | K6: Montant des
C7: Opérations assujetties à la TVA | D7: Total | F7: Exonéré | I7: Imposable | K7: droits (en DA)
B8: E3B11 | C8: Biens produits et denrées (art. 23 du CTVA) | J8: 0.09 | K8: =SUM(I8*7/100) -> 0
B9: E3B12 | C9: Prestations de services (art. 23 du CTVA) | J9: " | K9: =SUM(I9*7/100) -> 0
B10: E3B13 | C10: Opérations immobilières (art. 23 du CTVA) | J10: " | K10: =SUM(I10*7/100) -> 0
B11: E3B14 | C11: Actes Médicaux | J11: " | K11: =SUM(I11*7/100) -> 0
B12: E3B15 | C12: Commissionnaire £ cortiers | J12: " | K12: =SUM(I12*7/100) -> 0
B13: E3B16 | C13: Fournitured'énergie | J13: " | K13: =SUM(I13*7/100) -> 0
B16: E3B21 | C16: Production : biens, produits, denrées | J16: 0.19 | K16: =SUM(I16*19/100) -> 0
B17: E3B22 | C17: Revente en l'état : biens, produits, denrées GC | D17: =+F17+I17 -> 0 | F17: =+'CA-GC+TRANSPORT'!D9 -> 0 | I17: =+'CA-GC+TRANSPORT'!D15 -> 0 | J17: " | K17: =+I17*J16 -> 0
B18: E3B23 | C18: Travaux immobiliers autres que ceux de 7% | D18: =SUM(F18:I18) -> 0 | J18: " | K18: =+I18*0.19 -> 0
B19: E3B24 | C19: Professions Libérales | J19: " | K19: =ROUND(I19*17%,0) -> 0
B20: E3B25 | C20: Opérations de banques et assurances | J20: " | K20: =ROUND(I20*17%,0) -> 0
B21: E3B26 | C21: Prestations de téléphone et télex | J21: " | K21: =ROUND(I21*17%,0) -> 0
B22: E3B28 | C22: Autres prestations de services TRANSPORTS | D22: =+F22+I22 -> 146090 | I22: =+'CA-GC+TRANSPORT'!D28 -> 146090 | J22: 0.19 | K22: =I22*J22 -> 27757.1
B23: E3B31 | C23: Débits de boissons | J23: " | K23: =ROUND(I23*19%,0) -> 0
B24: E3B32 | C24: Production biens et denrées (art. 21 CTVA) | J24: " | K24: =ROUND(I24*19%,0) -> 0
B25: E3B33 | C25: Reventes en l'état (art. 21 CTVA) | J25: " | K25: =ROUND(I25*19%,0) -> 0
B26: E3B34 | C26: Tabacs et allumettes | J26: " | K26: =ROUND(I26*19%,0) -> 0
B27: E3B35 | C27: Spectacles jeux divertis autres | J27: " | K27: =ROUND(I27*19%,0) -> 0
B28: E3B36 | C28: Autres prestations (art. 21 CTVA) | J28: 0.19 | K28: =ROUND(I28*19%,0) -> 0
B29: E3B37 | C29: Consommations sur place | J29: " | K29: =SUM(I29*17/100) -> 0
C30: TOTAL GENERAL DES C.A | D30: =SUM(D8:E29) -> 146090 | F30: =SUM(F8:H29) -> 0 | I30: =SUM(I8:I29) -> 146090 | K30: =SUM(K16:L29) -> 27757.1 | M30: =+K17+K22 -> 27757.1
C31: B/ Déductions à opérer | G31: C/ TVA à Payer
C32: NATURE DES DEDUCTIONS | E32: MONTANT | G32: C | H32: - Total des droits dus | L32: =K30 -> 27757.1
B33: E3B91 | C33: Précompte antérieur | E33: 334502 | G33: E3B97 | H33: Régularisation du prorata
B34: E3B92 | C34: TVA / achats de matières et services (art.29 CTCA) | E34: =+'etat d''achat'!I13 -> 0 | H34: (art.40 CTCA)
B35: E3B93 | C35: TVA / achats biens amortissables (art.38 CTCA) | G35: E3B98 | H35: - Reversement (art.40 CTCA)
B36: E3B94 | C36: Régularisation prorata déduction (art.40 CTCA) | H36: TOTAL A RAPPELER (C) | L36: =L32+L33+L35 -> 27757.1
B37: E3B95 | C37: TVA / factures annulées ou imp (art.18 CTCA) | G37: B | H37: - Total des déductions | L37: =+E39 -> 334502
B38: E3B96 | C38: Autres déductions (Notification de précomptes, etc.) | G38: E3B00 | H38: A PAYER au titre du mois (C-B) | L38: =IF((L36-L37)>0,L36-L37,0) -> 0 | M38: 7
C39: Total des déductions a opérer(B) | E39: =+E34+E33 -> 334502 | H39: (A porter dans cadre récapitulation)
G40: E3B99 | H40: PRECOMPTE à reporter(B-C) | L40: =IF((L36-L37)<0,-L36+L37,0) -> 306744.9

Sheet PG-etat d'achat
B3: الجمهورية الجزائرية الديمقراطية الشعبية | CM3: Série G N°912(2025)
B4: REPUBLIQUE ALGERIENNE DEMOCRATIQUE ET POPULAIRE
B6: MINISTERE DES FINANCES | CW6: وزارة المالية
B7: Direction Générale des Impôts | CW7: المديرية العامة للضرائب
B8: Direction: | I8: =+'[3]Saisie-client'!C7 -> SIDI BEL ABBES | CW8: مديرية :
B9: Structure | I9: =+'[3]Saisie-client'!C10 -> SBA | CW9: المصلحة :
B11: کــشـــف المــورديــن
B12: ETAT DES FOURNISSEURS
B13: - المادة 29 من قانون الرسوم على رقم الاعمال
B14: - Article 29 du Code des Taxes sur le Chiffre d'Affaires-
AN15: Période | AS15: 46082
B18: يجب أن يرفق هذا الكشف بالتصريح الذي يقوم مقام حافظة إشعار بالتسديد سلسلة G رقم 50
B19: Le présent état doit être annexé à la déclaration tenant lieu de bordereau avis de versement série G N°50
B23: I – IDENTIFICATION DU CONTRIBUABLE | CV23: معلومات خاصة بالمكلف بالضريبة | CW23: I
B24: - Nom, Prénoms / Raison Sociale : | X24: SEKRANE BOUZIANE GROUPE COMMERCIAL & SERVICES DE TRANSPORTS | CV24: الاسم واللقب /اسم المؤسسة : | CW24: -
B25: - Adresse : | I25: CITE SALAMA DERRAR N°48 SIDI BEL ABBES | CV25: العنوان : | CW25: -
B26: - Numéro d’Identification Fiscale (NIF) | Z26: 1.9763102e+15 | CV26: رقم التعريف الحبائي : | CW26: -
B27: - Numéro d’Identification Fiscale (NIN) | CV27: رقم التعريف الوطني : | CW27: -
B28: - Numéro d’article d’imposition : | X28: 2245000012 | CV28: رقم المادة : | CW28: - | DF28: NEANT
B31: Arrêté le présent état contenant | AB31: page (s) numérotée(s) de 1 à | AY31: la somme totale de la taxe sur la valeur ajoutée déduite de
BD34: المبلغ الإجمالي للرسم على القيمة المضافة المخصوم | BK34: إلى | BY34: صفحة مرقمة من | CW34: يوقف حساب هذا الكشف وهو يحتوي على عدد
D38: J'atteste que les renseignements portés sur le présent état sont exacts. | CT38: أقر بصحة المعلومات الواردة في هذا الكشف
D39: A | F39: ='[3]Saisie-client'!C7 -> SIDI BEL ABBES | Q39: Le | S39: =TODAY() -> 46190 | CG39: في | CT39: بـ
D41: Signature du contribuable | CT41: إمضاء المكلف بالضريبة

Sheet etat d'achat
H2: Série G N°9 intercalaire (2025)
B4: رقم التعريف الوطني | C4: رقم التعريف الجبائي | D4: العنوان | E4: رقم التسجيل في السجل التجاري | F4: تاريخ الفاتورة أو أي مستند بدلا من ذلك | G4: مرجع الفاتورة أو أي مستند بدلا من ذلك | H4: مبلغ المشتريات المنجزة أو الخدمات المقدمة مع احتساب كل الرسوم | I4: مبلغ الرسم علي القيمة المضافة المخصوم (*)
B5: Numéro d'Identification national (NIN) | C5: Numéro d'identifiant fiscale (NIF) | D5: Adresse | E5: Numéro d'inscription au registre de commerce | F5: Date de la facture ou autres. documents tenant lieu | G5: Référence de la facture ou autres documents tenant lieu | H5: Montant TTC des achats effectués ou des prestations reçues | I5: Montant de la taxe sur la valeur ajoutée déduite (*)
H13: =SUM(H6:H12) -> 0 | I13: =+I6+I7+I8 -> 0
B15: (*) الرسم على القيمة الواجب ذكره هو الرسم المخصوم فعليا خلال الشهر أو الفترة المعنية موضوع هذا الكشف مع الأخذ بعين الاعتبار الحدث المنشئ لهذا الرسم.
B16: (*)La TVA à mentionner est celle effectivement déduite durant le mois ou la période considérée, objet de cet état fournisseurs, tenant compte du fait générateur de cette taxe.
B17: Page n".... | I17: رقم الصفحة
H20: Série G N°9 intercalaire (2025)
B22: رقم التعريف الوطني | C22: رقم التعريف الجبائي | D22: العنوان | E22: رقم التسجيل في السجل التجاري | F22: تاريخ الفاتورة أو أي مستند بدلا من ذلك | G22: مرجع الفاتورة أو أي مستند بدلا من ذلك | H22: مبلغ المشتريات المنجزة أو الخدمات المقدمة مع احتساب كل الرسوم | I22: مبلغ الرسم علي القيمة المضافة المخصوم (*)
B23: Numéro d'Identification national (NIN) | C23: Numéro d'identifiant fiscale (NIF) | D23: Adresse | E23: Numéro d'inscription au registre de commerce | F23: Date de la facture ou autres. documents tenant lieu | G23: Référence de la facture ou autres documents tenant lieu | H23: Montant TTC des achats effectués ou des prestations reçues | I23: Montant de la taxe sur la valeur ajoutée déduite (*)
G24: REPORT*** | H24: 0 | I24: 0
H31: =I31/0.19 -> 0
H32: =I32/0.19 -> 0
H33: =I33/0.19 -> 0
H34: =I34/0.19 -> 0
H35: =I35/0.19 -> 0
H36: =I36/0.19 -> 0
H37: =I37/0.19 -> 0
H38: =I38/0.19 -> 0
H39: =I39/0.19 -> 0
H40: =I40/0.19 -> 0
G41: TOTAL | H41: =SUM(H24:H40) -> 0 | I41: =SUM(I24:I40) -> 0
B43: (*) الرسم على القيمة الواجب ذكره هو الرسم المخصوم فعليا خلال الشهر أو الفترة المعنية موضوع هذا الكشف مع الأخذ بعين الاعتبار الحدث المنشئ لهذا الرسم.
B44: (*)La TVA à mentionner est celle effectivement déduite durant le mois ou la période considérée, objet de cet état fournisseurs, tenant compte du fait générateur de cette taxe.
B45: Page n".... | I45: رقم الصفحة

Sheet CA-GC+TRANSPORT
B3: G50-AVRIL - | C3: RELEVE DU 01/04 AU 30/04/2026 | E3: GROUPE COMMERCIAL
B5: DATE | C5: TTC | D5: HT | E5: TVA
A6: EXO | B6: 46118 | D6: =+C6/1.19 -> 0
B7: 46118 | D7: =+C7/1.19 -> 0
B8: 46124 | D8: =+C8/1.19 -> 0
D9: =SUM(D6:D8) -> 0
A11: IMPO
B12: 46140 | D12: =+C12/1.19 -> 0 | E12: =+D12*19% -> 0
D15: =SUM(D12:D14) -> 0
C17: =SUM(C6:C14) -> 0 | D17: =+D15+D9 -> 0 | E17: =SUM(E6:E14) -> 0
B20: RELEVE DU 01/02 AU 28/02/2026 | D20: TRANSPORT
B22: DATE | C22: TTC | D22: HT | E22: TVA
C24: 173847.1 | D24: =+C24/1.19 -> 146090 | E24: =+D24*19% -> 27757.1
C28: =SUM(C23:C27) -> 173847.1 | D28: =SUM(D23:D27) -> 146090 | E28: =SUM(E23:E27) -> 27757.1
C30: HT TOAL | D30: =+D28+D17 -> 146090
C31: TVA TOTAL | D31: =+E28+E17 -> 27757.1
